isItLikely/__init__.py
isItLikely/myfunctions.py
isItLikely-0.1.0.dist-info/METADATA
isItLikely-0.1.0.dist-info/WHEEL
isItLikely-0.1.0.dist-info/top_level.txt
isItLikely-0.1.0.dist-info/RECORD
