Metadata-Version: 2.1
Name: isItLikely
Version: 0.1.0
Summary: Probablity Library
Home-page: UNKNOWN
Author: M4K4TT4CK
License: MIT
Platform: UNKNOWN
